{
  "date": "2026-07-14",
  "generated_at": "2026-07-14T06:31:38+03:00",
  "articles": [
    {
      "id": "A",
      "title": "Bison rams grandfather in Yellowstone Park, knocking him metres into the air",
      "article_url": "https://www.bbc.co.uk/news/articles/c2dy9krpydlo",
      "task_data_url": "data/tasks/2026-07-14-A.json",
      "task_count": 10
    },
    {
      "id": "B",
      "title": "'There was no way to get out': Witnesses describe how deadly inferno swept through Bangkok bar",
      "article_url": "https://www.bbc.co.uk/news/articles/crr8gnx01d7o",
      "task_data_url": "data/tasks/2026-07-14-B.json",
      "task_count": 10
    },
    {
      "id": "C",
      "title": "The secretive crypto firm backed by Farage's biggest donor",
      "article_url": "https://www.bbc.co.uk/news/articles/cg4w6wqye32o",
      "task_data_url": "data/tasks/2026-07-14-C.json",
      "task_count": 10
    }
  ]
}