{
  "date": "2026-07-11",
  "id": "A",
  "level": "A",
  "level_label": "A — Easier English",
  "title": "New dinosaur species as long as cricket pitch discovered in Thailand",
  "source": "BBC",
  "url": "https://www.bbc.co.uk/news/articles/crely7g8xepo?at_medium=RSS&at_campaign=rss",
  "word_count": 392,
  "generated_at": "2026-07-11T09:08:30.999771+00:00",
  "difficulty_reason": "Short, direct science story with one clear discovery and simple sentence structure; mostly B1/B2 vocabulary and little background knowledge needed.",
  "settings": {
    "source_mode": "BBC-only",
    "vocabulary_count": 15,
    "quiz_enabled": true
  },
  "words": [
    {
      "word": "fossils",
      "lemma": "fossil",
      "level": "B2",
      "hebrew": "מְאוּבָּנִים",
      "explanation_hebrew": "שרידים מאובנים של יצורים קדומים בסלע",
      "pronunciation_hebrew": "פוֹסִילְז",
      "example": "The museum displays dinosaur fossils."
    },
    {
      "word": "specimen",
      "lemma": "specimen",
      "level": "C1",
      "hebrew": "דָּגֶם, פריט לדוגמה",
      "explanation_hebrew": "פריט בודד המשמש לבחינה או למחקר",
      "pronunciation_hebrew": "סְפֶּסִימֶן",
      "example": "They studied a rare specimen of the plant."
    },
    {
      "word": "fragments",
      "lemma": "fragment",
      "level": "B2",
      "hebrew": "שְׁבָרִים, רסיסים",
      "explanation_hebrew": "חלקים קטנים שנשברו מדבר שלם",
      "pronunciation_hebrew": "פְרַגְמֶנְטְס",
      "example": "They found fragments of ancient pottery."
    },
    {
      "word": "resembling",
      "lemma": "resemble",
      "level": "B2",
      "hebrew": "דּוֹמֶה ל-",
      "explanation_hebrew": "שנראה או מזכיר דבר אחר",
      "pronunciation_hebrew": "רִיזֶמְבְּלִינְג",
      "example": "He found stones resembling eggs."
    },
    {
      "word": "excavated",
      "lemma": "excavate",
      "level": "C1",
      "hebrew": "נֶחְפַּר, נחשף בחפירה",
      "explanation_hebrew": "הוצא מהאדמה בעבודת חפירה",
      "pronunciation_hebrew": "אֶקְסְקַבֵייטֶד",
      "example": "Archaeologists excavated the old city."
    },
    {
      "word": "distinctive",
      "lemma": "distinctive",
      "level": "B2",
      "hebrew": "מְיוּחָד, ייחודי",
      "explanation_hebrew": "בעל תכונות בולטות המבדילות אותו",
      "pronunciation_hebrew": "דִיסְטִינְקְטִיב",
      "example": "The bird has a distinctive call."
    },
    {
      "word": "characteristics",
      "lemma": "characteristic",
      "level": "B2",
      "hebrew": "מְאַפְיֵנִים, תכונות",
      "explanation_hebrew": "תכונות טיפוסיות של דבר או יצור",
      "pronunciation_hebrew": "קַרַקְטֶרִיסְטִיקְס",
      "example": "Each animal has unique characteristics."
    },
    {
      "word": "vegetation",
      "lemma": "vegetation",
      "level": "B2",
      "hebrew": "צִמְחִיָּה",
      "explanation_hebrew": "כלל הצמחים הגדלים באזור מסוים",
      "pronunciation_hebrew": "וֶגֶ'טֵיישֶן",
      "example": "The valley was covered in thick vegetation."
    },
    {
      "word": "herbivore",
      "lemma": "herbivore",
      "level": "C1",
      "hebrew": "אוֹכֵל צמחים, צמחוני",
      "explanation_hebrew": "בעל חיים הניזון מצמחים בלבד",
      "pronunciation_hebrew": "הֶרְבִּיבוֹר",
      "example": "A cow is a herbivore."
    },
    {
      "word": "exhilarated",
      "lemma": "exhilarate",
      "level": "C1",
      "hebrew": "נִרְגָּשׁ מאוד, נסער משמחה",
      "explanation_hebrew": "חש התרגשות עזה ושמחה גדולה",
      "pronunciation_hebrew": "אֶגְזִילַרֵייטֶד",
      "example": "She felt exhilarated after the race."
    },
    {
      "word": "relieved",
      "lemma": "relieve",
      "level": "B2",
      "hebrew": "מוּקָל, חש הקלה",
      "explanation_hebrew": "חש הקלה לאחר דאגה או מתח",
      "pronunciation_hebrew": "רִילִיבְד",
      "example": "He was relieved when the test ended."
    },
    {
      "word": "serpent",
      "lemma": "serpent",
      "level": "C1",
      "hebrew": "נָחָשׁ (ספרותי)",
      "explanation_hebrew": "מילה ספרותית לנחש",
      "pronunciation_hebrew": "סֶרְפֶּנְט",
      "example": "The legend spoke of a giant serpent."
    },
    {
      "word": "survey",
      "lemma": "survey",
      "level": "B2",
      "hebrew": "סֶקֶר, סקירה",
      "explanation_hebrew": "בדיקה או סקירה שיטתית של אזור או נושא",
      "pronunciation_hebrew": "סַרְוֵויי",
      "example": "The team carried out a survey of the area."
    },
    {
      "word": "recovered",
      "lemma": "recover",
      "level": "B2",
      "hebrew": "הוּשַׁב, נמצא ונאסף",
      "explanation_hebrew": "הושג בחזרה או נאסף ממקום",
      "pronunciation_hebrew": "רִיקָבֶרְד",
      "example": "Divers recovered items from the wreck."
    },
    {
      "word": "arrangement",
      "lemma": "arrangement",
      "level": "B2",
      "hebrew": "סִידּוּר, מבנה",
      "explanation_hebrew": "האופן שבו דברים מסודרים יחד",
      "pronunciation_hebrew": "אֲרֵיינְגְ'מֶנְט",
      "example": "The bones had an unusual arrangement."
    }
  ],
  "quiz": [
    {
      "id": "A-q1",
      "word": "fossils",
      "type": "english_to_hebrew",
      "question": "What does “fossils” mean?",
      "options": [
        "גלים",
        "מְאוּבָּנִים",
        "פרחים",
        "עננים"
      ],
      "correct_answer": "מְאוּבָּנִים",
      "explanation_hebrew": "“fossils” פירושו מְאוּבָּנִים. שרידים מאובנים של יצורים קדומים בסלע."
    },
    {
      "id": "A-q2",
      "word": "specimen",
      "type": "hebrew_to_english",
      "question": "איזו מילה באנגלית משמעותה “דָּגֶם, פריט לדוגמה”?",
      "options": [
        "specimen",
        "copy",
        "crowd",
        "waste"
      ],
      "correct_answer": "specimen",
      "explanation_hebrew": "המילה specimen משמעה דָּגֶם, פריט לדוגמה. פריט בודד המשמש לבחינה או למחקר."
    },
    {
      "id": "A-q3",
      "word": "fragments",
      "type": "english_to_hebrew",
      "question": "What does “fragments” mean?",
      "options": [
        "שְׁבָרִים, רסיסים",
        "קירות",
        "עמודים",
        "גושים שלמים"
      ],
      "correct_answer": "שְׁבָרִים, רסיסים",
      "explanation_hebrew": "“fragments” פירושו שְׁבָרִים, רסיסים. חלקים קטנים שנשברו מדבר שלם."
    },
    {
      "id": "A-q4",
      "word": "resembling",
      "type": "hebrew_to_english",
      "question": "איזו מילה באנגלית משמעותה “דּוֹמֶה ל-”?",
      "options": [
        "opposing",
        "breaking",
        "hiding",
        "resembling"
      ],
      "correct_answer": "resembling",
      "explanation_hebrew": "המילה resembling משמעה דּוֹמֶה ל-. שנראה או מזכיר דבר אחר."
    },
    {
      "id": "A-q5",
      "word": "excavated",
      "type": "english_to_hebrew",
      "question": "What does “excavated” mean?",
      "options": [
        "נקבר",
        "הוסתר",
        "נֶחְפַּר, נחשף בחפירה",
        "נזרק"
      ],
      "correct_answer": "נֶחְפַּר, נחשף בחפירה",
      "explanation_hebrew": "“excavated” פירושו נֶחְפַּר, נחשף בחפירה. הוצא מהאדמה בעבודת חפירה."
    },
    {
      "id": "A-q6",
      "word": "distinctive",
      "type": "hebrew_to_english",
      "question": "איזו מילה באנגלית משמעותה “מְיוּחָד, ייחודי”?",
      "options": [
        "distinctive",
        "common",
        "ordinary",
        "plain"
      ],
      "correct_answer": "distinctive",
      "explanation_hebrew": "המילה distinctive משמעה מְיוּחָד, ייחודי. בעל תכונות בולטות המבדילות אותו."
    },
    {
      "id": "A-q7",
      "word": "characteristics",
      "type": "english_to_hebrew",
      "question": "What does “characteristics” mean?",
      "options": [
        "מְאַפְיֵנִים, תכונות",
        "טעויות",
        "מקריות",
        "חיקויים"
      ],
      "correct_answer": "מְאַפְיֵנִים, תכונות",
      "explanation_hebrew": "“characteristics” פירושו מְאַפְיֵנִים, תכונות. תכונות טיפוסיות של דבר או יצור."
    },
    {
      "id": "A-q8",
      "word": "vegetation",
      "type": "hebrew_to_english",
      "question": "איזו מילה באנגלית משמעותה “צִמְחִיָּה”?",
      "options": [
        "vegetation",
        "rocks",
        "metal",
        "sand"
      ],
      "correct_answer": "vegetation",
      "explanation_hebrew": "המילה vegetation משמעה צִמְחִיָּה. כלל הצמחים הגדלים באזור מסוים."
    },
    {
      "id": "A-q9",
      "word": "herbivore",
      "type": "english_to_hebrew",
      "question": "What does “herbivore” mean?",
      "options": [
        "טורף",
        "טפיל",
        "אוֹכֵל צמחים, צמחוני",
        "אוכל כול"
      ],
      "correct_answer": "אוֹכֵל צמחים, צמחוני",
      "explanation_hebrew": "“herbivore” פירושו אוֹכֵל צמחים, צמחוני. בעל חיים הניזון מצמחים בלבד."
    },
    {
      "id": "A-q10",
      "word": "exhilarated",
      "type": "hebrew_to_english",
      "question": "איזו מילה באנגלית משמעותה “נִרְגָּשׁ מאוד, נסער משמחה”?",
      "options": [
        "exhilarated",
        "gloomy",
        "calm",
        "bored"
      ],
      "correct_answer": "exhilarated",
      "explanation_hebrew": "המילה exhilarated משמעה נִרְגָּשׁ מאוד, נסער משמחה. חש התרגשות עזה ושמחה גדולה."
    },
    {
      "id": "A-q11",
      "word": "relieved",
      "type": "english_to_hebrew",
      "question": "What does “relieved” mean?",
      "options": [
        "מודאג",
        "מוּקָל, חש הקלה",
        "מתוח",
        "מפוחד"
      ],
      "correct_answer": "מוּקָל, חש הקלה",
      "explanation_hebrew": "“relieved” פירושו מוּקָל, חש הקלה. חש הקלה לאחר דאגה או מתח."
    },
    {
      "id": "A-q12",
      "word": "serpent",
      "type": "hebrew_to_english",
      "question": "איזו מילה באנגלית משמעותה “נָחָשׁ (ספרותי)”?",
      "options": [
        "fish",
        "serpent",
        "bird",
        "insect"
      ],
      "correct_answer": "serpent",
      "explanation_hebrew": "המילה serpent משמעה נָחָשׁ (ספרותי). מילה ספרותית לנחש."
    },
    {
      "id": "A-q13",
      "word": "survey",
      "type": "english_to_hebrew",
      "question": "What does “survey” mean?",
      "options": [
        "חלום",
        "שמועה",
        "ניחוש",
        "סֶקֶר, סקירה"
      ],
      "correct_answer": "סֶקֶר, סקירה",
      "explanation_hebrew": "“survey” פירושו סֶקֶר, סקירה. בדיקה או סקירה שיטתית של אזור או נושא."
    },
    {
      "id": "A-q14",
      "word": "recovered",
      "type": "hebrew_to_english",
      "question": "איזו מילה באנגלית משמעותה “הוּשַׁב, נמצא ונאסף”?",
      "options": [
        "recovered",
        "destroyed",
        "lost",
        "dropped"
      ],
      "correct_answer": "recovered",
      "explanation_hebrew": "המילה recovered משמעה הוּשַׁב, נמצא ונאסף. הושג בחזרה או נאסף ממקום."
    },
    {
      "id": "A-q15",
      "word": "arrangement",
      "type": "english_to_hebrew",
      "question": "What does “arrangement” mean?",
      "options": [
        "פיזור",
        "סִידּוּר, מבנה",
        "הרס",
        "בלגן"
      ],
      "correct_answer": "סִידּוּר, מבנה",
      "explanation_hebrew": "“arrangement” פירושו סִידּוּר, מבנה. האופן שבו דברים מסודרים יחד."
    }
  ]
}