{
  "version": 1,
  "date": "2026-07-21",
  "generated_at": "2026-07-21T10:25:49.996101+00:00",
  "track": "Essential English 3000",
  "lesson_size": 15,
  "selection": {
    "new_count": 15,
    "review_count": 0,
    "rule": "Known words are excluded; due review words are prioritized; remaining places use unseen core words."
  },
  "profile_summary": {
    "bank_size": 113,
    "known_count": 60,
    "learning_count": 0,
    "remaining_count": 53,
    "profile_updated_at": "2026-07-21T10:25:49.901354+00:00"
  },
  "words": [
    {
      "id": "core-0030",
      "word": "manage",
      "part_of_speech": "verb",
      "level": "B1",
      "hebrew": "לנהל / להצליח",
      "pronunciation_hebrew": "מֶנֶג'",
      "explanation_hebrew": "לשלוט במשימה או להצליח לבצע דבר קשה.",
      "example": "She managed to finish the work on time.",
      "reason": "new",
      "position": 1
    },
    {
      "id": "core-0099",
      "word": "feature",
      "part_of_speech": "noun",
      "level": "B1",
      "hebrew": "תכונה / מאפיין",
      "pronunciation_hebrew": "פִיצֶ'ר",
      "explanation_hebrew": "חלק או יכולת בולטים של מוצר או מערכת.",
      "example": "The app includes a useful review feature.",
      "reason": "new",
      "position": 2
    },
    {
      "id": "core-0096",
      "word": "context",
      "part_of_speech": "noun",
      "level": "B1",
      "hebrew": "הקשר",
      "pronunciation_hebrew": "קוֹנְטֶקְסְט",
      "explanation_hebrew": "המידע סביב מילה או אירוע שעוזר להבין אותו.",
      "example": "The context makes the meaning clear.",
      "reason": "new",
      "position": 3
    },
    {
      "id": "core-0109",
      "word": "reliable",
      "part_of_speech": "adjective",
      "level": "B2",
      "hebrew": "אמין",
      "pronunciation_hebrew": "רִילַיְאַבְּל",
      "explanation_hebrew": "ניתן לסמוך עליו שיפעל או יספק מידע נכון.",
      "example": "We need a reliable data source.",
      "reason": "new",
      "position": 4
    },
    {
      "id": "core-0078",
      "word": "necessary",
      "part_of_speech": "adjective",
      "level": "B1",
      "hebrew": "הכרחי",
      "pronunciation_hebrew": "נֶסֶסֶרִי",
      "explanation_hebrew": "נדרש כדי שדבר יקרה או יצליח.",
      "example": "Regular review is necessary for long-term memory.",
      "reason": "new",
      "position": 5
    },
    {
      "id": "core-0007",
      "word": "benefit",
      "part_of_speech": "noun",
      "level": "B1",
      "hebrew": "תועלת / יתרון",
      "pronunciation_hebrew": "בֶּנֶפִיט",
      "explanation_hebrew": "דבר טוב שמתקבל מפעולה או מצב.",
      "example": "Regular practice has a clear benefit.",
      "reason": "new",
      "position": 6
    },
    {
      "id": "core-0044",
      "word": "relate",
      "part_of_speech": "verb",
      "level": "B1",
      "hebrew": "לקשר / להתייחס",
      "pronunciation_hebrew": "רִילֵייט",
      "explanation_hebrew": "להראות קשר בין דברים או להתייחס לנושא.",
      "example": "The questions relate to the article.",
      "reason": "new",
      "position": 7
    },
    {
      "id": "core-0032",
      "word": "occur",
      "part_of_speech": "verb",
      "level": "B2",
      "hebrew": "להתרחש",
      "pronunciation_hebrew": "אֶקֶר",
      "explanation_hebrew": "לקרות, בדרך כלל בהקשר רשמי יותר.",
      "example": "The fault occurred during the experiment.",
      "reason": "new",
      "position": 8
    },
    {
      "id": "core-0077",
      "word": "method",
      "part_of_speech": "noun",
      "level": "B1",
      "hebrew": "שיטה",
      "pronunciation_hebrew": "מֶתֶד",
      "explanation_hebrew": "דרך מסודרת לבצע משימה.",
      "example": "This method is easy to apply.",
      "reason": "new",
      "position": 9
    },
    {
      "id": "core-0094",
      "word": "confirm",
      "part_of_speech": "verb",
      "level": "B1",
      "hebrew": "לאשר / לוודא",
      "pronunciation_hebrew": "קַנְפֶרְם",
      "explanation_hebrew": "להראות שדבר נכון או לבדוק שהוא אכן נכון.",
      "example": "Please confirm the meeting time.",
      "reason": "new",
      "position": 10
    },
    {
      "id": "core-0098",
      "word": "estimate",
      "part_of_speech": "verb",
      "level": "B2",
      "hebrew": "להעריך",
      "pronunciation_hebrew": "אֶסְטִימֵייט",
      "explanation_hebrew": "לחשב בקירוב כמות או ערך.",
      "example": "We can estimate the cost before ordering.",
      "reason": "new",
      "position": 11
    },
    {
      "id": "core-0112",
      "word": "select",
      "part_of_speech": "verb",
      "level": "B1",
      "hebrew": "לבחור",
      "pronunciation_hebrew": "סִילֶקְט",
      "explanation_hebrew": "לבחור פריט אחד או יותר מתוך קבוצה.",
      "example": "Select the correct answer.",
      "reason": "new",
      "position": 12
    },
    {
      "id": "core-0054",
      "word": "value",
      "part_of_speech": "noun",
      "level": "B1",
      "hebrew": "ערך / חשיבות",
      "pronunciation_hebrew": "וַלְיוּ",
      "explanation_hebrew": "החשיבות או התועלת של דבר.",
      "example": "Examples add value to a vocabulary lesson.",
      "reason": "new",
      "position": 13
    },
    {
      "id": "core-0019",
      "word": "encourage",
      "part_of_speech": "verb",
      "level": "B1",
      "hebrew": "לעודד",
      "pronunciation_hebrew": "אִנְקַרִג'",
      "explanation_hebrew": "לתת תמיכה או ביטחון כדי שמישהו יעשה משהו.",
      "example": "Good teachers encourage students to ask questions.",
      "reason": "new",
      "position": 14
    },
    {
      "id": "core-0089",
      "word": "alternative",
      "part_of_speech": "noun",
      "level": "B2",
      "hebrew": "חלופה",
      "pronunciation_hebrew": "אוֹלְטֶרְנָטִיב",
      "explanation_hebrew": "אפשרות אחרת שניתן לבחור במקום הקיימת.",
      "example": "We should consider an alternative solution.",
      "reason": "new",
      "position": 15
    }
  ]
}
